ml_trainer/__init__.py
ml_trainer/auto_trainer.py
ml_trainer/config.py
ml_trainer/trainer.py
ml_trainer/base/__init__.py
ml_trainer/base/base_dataset.py
ml_trainer/base/base_model.py
ml_trainer/examples/__init__.py
ml_trainer/examples/clearml_trainer_runner.py
ml_trainer/tasks/__init__.py
ml_trainer/tasks/distributed_llm_finetuning.py
ml_trainer/tasks/image_classification.py
ml_trainer/tasks/image_segmentation.py
ml_trainer/tasks/llm_finetuning.py
ml_trainer/tasks/tabular_classification.py
ml_trainer/tasks/task_factory.py
ml_trainer/tasks/task_registry.py
ml_trainer/tasks/text_prediction.py
ml_trainer/tasks/timeseries.py
ml_trainer/tasks/tslib/__init__.py
ml_trainer/tasks/tslib/run.py
ml_trainer/tasks/tslib/data_provider/__init__.py
ml_trainer/tasks/tslib/data_provider/data_factory.py
ml_trainer/tasks/tslib/data_provider/data_loader.py
ml_trainer/tasks/tslib/data_provider/m4.py
ml_trainer/tasks/tslib/data_provider/uea.py
ml_trainer/tasks/tslib/exp/__init__.py
ml_trainer/tasks/tslib/exp/exp_anomaly_detection.py
ml_trainer/tasks/tslib/exp/exp_basic.py
ml_trainer/tasks/tslib/exp/exp_classification.py
ml_trainer/tasks/tslib/exp/exp_imputation.py
ml_trainer/tasks/tslib/exp/exp_long_term_forecasting.py
ml_trainer/tasks/tslib/exp/exp_short_term_forecasting.py
ml_trainer/tasks/tslib/layers/AutoCorrelation.py
ml_trainer/tasks/tslib/layers/Autoformer_EncDec.py
ml_trainer/tasks/tslib/layers/Conv_Blocks.py
ml_trainer/tasks/tslib/layers/Crossformer_EncDec.py
ml_trainer/tasks/tslib/layers/DWT_Decomposition.py
ml_trainer/tasks/tslib/layers/ETSformer_EncDec.py
ml_trainer/tasks/tslib/layers/Embed.py
ml_trainer/tasks/tslib/layers/FourierCorrelation.py
ml_trainer/tasks/tslib/layers/MultiWaveletCorrelation.py
ml_trainer/tasks/tslib/layers/Pyraformer_EncDec.py
ml_trainer/tasks/tslib/layers/SelfAttention_Family.py
ml_trainer/tasks/tslib/layers/StandardNorm.py
ml_trainer/tasks/tslib/layers/Transformer_EncDec.py
ml_trainer/tasks/tslib/layers/__init__.py
ml_trainer_sdk-0.4.1.10.dist-info/METADATA
ml_trainer_sdk-0.4.1.10.dist-info/WHEEL
ml_trainer_sdk-0.4.1.10.dist-info/top_level.txt
ml_trainer_sdk-0.4.1.10.dist-info/RECORD
