Metadata-Version: 2.4
Name: ml-trainer-sdk
Version: 0.4.1.10
Summary: A modular SDK for training ML models (image, tabular, timeseries, etc.)
Author: Hypnotic
Requires-Python: >=3.10
Requires-Dist: torch==2.6.0
Requires-Dist: torchvision==0.21.0
Requires-Dist: numpy==1.26.4
Requires-Dist: pandas==2.2.3
Requires-Dist: scikit-learn==1.4.2
Requires-Dist: matplotlib==3.10.1
Requires-Dist: tensorboard==2.19.0
Requires-Dist: Cython==3.1.1
Requires-Dist: datasets<4.2,>=3.4.1
Requires-Dist: unsloth
Requires-Dist: unsloth_zoo
Requires-Dist: torchao==0.12.0
Requires-Dist: patool==4.0.1
Requires-Dist: reformer-pytorch==1.4.4
Requires-Dist: sktime==0.39.0
Requires-Dist: PyWavelets==1.8.0
Requires-Dist: timm==1.0.20
Requires-Dist: axolotl==0.12.2
Dynamic: author
Dynamic: requires-dist
Dynamic: requires-python
Dynamic: summary
